README.rst
setup.py
tinap/__init__.py
tinap/doh.py
tinap/forwarder.py
tinap/throttler.py
tinap/util.py
tinap.egg-info/PKG-INFO
tinap.egg-info/SOURCES.txt
tinap.egg-info/dependency_links.txt
tinap.egg-info/entry_points.txt
tinap.egg-info/not-zip-safe
tinap.egg-info/top_level.txt
tinap/tests/__init__.py
tinap/tests/support.py
tinap/tests/test_fwd.py