Metadata-Version: 1.0
Name: tinap
Version: 0.2
Summary: Port forwarding with traffic shaping
Home-page: https://github.com/tarekziade/tinap
Author: Tarek Ziadé
Author-email: tarek@mozilla.com
License: UNKNOWN
Platform: UNKNOWN
